Tutorials/__init__.py
booleabayes/__init__.py
booleabayes/enrichr.py
booleabayes/load.py
booleabayes/make_tf_network.py
booleabayes/mp_rw.py
booleabayes/plot.py
booleabayes/proc.py
booleabayes/rw.py
booleabayes/tl.py
booleabayes/utils.py
booleabayes-1.0.0.dist-info/LICENSE
booleabayes-1.0.0.dist-info/METADATA
booleabayes-1.0.0.dist-info/WHEEL
booleabayes-1.0.0.dist-info/top_level.txt
booleabayes-1.0.0.dist-info/RECORD
